squaternion/__init__.py
squaternion/squaternion.py
squaternion-2025.3.2.dist-info/METADATA
squaternion-2025.3.2.dist-info/WHEEL
squaternion-2025.3.2.dist-info/RECORD
