Metadata-Version: 2.1
Name: squaternion
Version: 2025.3.2
Summary: Some simple functions for quaternion math
Home-page: https://pypi.org/project/squaternion/
License: MIT
Keywords: rotations,quaternion,euler
Author: walchko
Author-email: walchko@users.noreply.github.com
Requires-Python: >=3.9
Classifier: Development Status :: 4 - Beta
Classifier: Intended Audience :: Developers
Classifier: License :: OSI Approved :: MIT License
Classifier: Operating System :: OS Independent
Classifier: Programming Language :: Python :: 3
Classifier: Programming Language :: Python :: 3.9
Classifier: Programming Language :: Python :: 3.10
Classifier: Programming Language :: Python :: 3.11
Classifier: Programming Language :: Python :: 3.12
Classifier: Programming Language :: Python :: 3.13
Classifier: Topic :: Software Development :: Libraries
Classifier: Topic :: Software Development :: Libraries :: Application Frameworks
Classifier: Topic :: Software Development :: Libraries :: Python Modules
Project-URL: Repository, https://github.com/the-guild-of-calamitous-intent/squaternion
